timesat_cli/__init__.py
timesat_cli/__main__.py
timesat_cli/config.py
timesat_cli/config_s3.py
timesat_cli/csvutils.py
timesat_cli/dateutils.py
timesat_cli/fsutils.py
timesat_cli/processing.py
timesat_cli/qa.py
timesat_cli/readers.py
timesat_cli/writers.py
timesat_engine/__init__.py
timesat_engine/config.py
timesat_engine/config_s3.py
timesat_engine/csvutils.py
timesat_engine/dateutils.py
timesat_engine/fsutils.py
timesat_engine/processing.py
timesat_engine/qa.py
timesat_engine/readers.py
timesat_engine/writers.py
timesat_cli-1.5.2.dist-info/METADATA
timesat_cli-1.5.2.dist-info/WHEEL
timesat_cli-1.5.2.dist-info/entry_points.txt
timesat_cli-1.5.2.dist-info/licenses/LICENSE
timesat_cli-1.5.2.dist-info/licenses/NOTICE
timesat_cli-1.5.2.dist-info/RECORD
