Metadata-Version: 2.4
Name: timesat-cli
Version: 1.5.2
Summary: Python-based command line interface for TIMESAT
Author: Zhanzhang Cai
License: MIT
License-File: LICENSE
License-File: NOTICE
Classifier: Development Status :: 5 - Production/Stable
Classifier: Environment :: Console
Classifier: Intended Audience :: Science/Research
Classifier: License :: OSI Approved :: MIT License
Classifier: Operating System :: OS Independent
Classifier: Programming Language :: Python :: 3
Classifier: Topic :: Scientific/Engineering :: GIS
Requires-Python: >=3.10
Requires-Dist: boto3
Requires-Dist: numpy
Requires-Dist: pandas
Requires-Dist: python-dotenv
Requires-Dist: rasterio
Requires-Dist: timesat<4.3,>=4.2.1
